ipytablewidgets/__init__.py
ipytablewidgets/_frontend.py
ipytablewidgets/_version.py
ipytablewidgets/compressors.py
ipytablewidgets/numpy_adapter.py
ipytablewidgets/pandas_adapter.py
ipytablewidgets/progressivis_adapter.py
ipytablewidgets/serializers.py
ipytablewidgets/source_adapter.py
ipytablewidgets/traitlets.py
ipytablewidgets/widgets.py
ipytablewidgets/labextension/package.json
ipytablewidgets/labextension/static/149.40f4249249bc14416a21.js
ipytablewidgets/labextension/static/261.bc115825a135ccbef0e9.js
ipytablewidgets/labextension/static/405.6e1d012d86b0ed03bddf.js
ipytablewidgets/labextension/static/424.e42e48076aba64887fd2.js
ipytablewidgets/labextension/static/568.46074a0ad0e0cb2bad6c.js
ipytablewidgets/labextension/static/861.78ea6fdd74d109f94c90.js
ipytablewidgets/labextension/static/861.78ea6fdd74d109f94c90.js.LICENSE.txt
ipytablewidgets/labextension/static/remoteEntry.830facb2b8d2798f80f1.js
ipytablewidgets/labextension/static/style.js
ipytablewidgets/labextension/static/third-party-licenses.json
ipytablewidgets/static/extension.js
ipytablewidgets/static/index.js
ipytablewidgets/static/index.js.LICENSE.txt
ipytablewidgets/tests/__init__.py
ipytablewidgets/tests/test_compression.py
ipytablewidgets/tests/test_frontend_version.py
ipytablewidgets/tests/test_serialization.py
ipytablewidgets/tests/test_table.py
ipytablewidgets/tests/test_traitlets.py
ipytablewidgets-0.3.1.data/data/etc/jupyter/nbconfig/notebook.d/jupyter-tablewidgets.json
ipytablewidgets-0.3.1.data/data/share/jupyter/labextensions/jupyter-tablewidgets/install.json
ipytablewidgets-0.3.1.data/data/share/jupyter/labextensions/jupyter-tablewidgets/package.json
ipytablewidgets-0.3.1.data/data/share/jupyter/labextensions/jupyter-tablewidgets/static/149.40f4249249bc14416a21.js
ipytablewidgets-0.3.1.data/data/share/jupyter/labextensions/jupyter-tablewidgets/static/261.bc115825a135ccbef0e9.js
ipytablewidgets-0.3.1.dist-info/LICENSE
ipytablewidgets-0.3.1.dist-info/METADATA
ipytablewidgets-0.3.1.dist-info/WHEEL
ipytablewidgets-0.3.1.dist-info/top_level.txt
ipytablewidgets-0.3.1.dist-info/RECORD
