Metadata-Version: 2.1
Name: ipytablewidgets
Version: 0.3.1
Summary: A set of widgets to help facilitate reuse of large tables across widgets
Home-page: https://github.com/progressivis/ipytablewidgets
Author: Jean-Daniel Fekete, Christian Poli
Author-email: ipytablewidgets@inria.fr
License: BSD-3-Clause
Keywords: ipython,jupyter,widgets
Platform: Linux
Platform: Mac OS X
Platform: Windows
Requires-Python: >=3.7
License-File: LICENSE
